pulumi_ns1/__init__.py
pulumi_ns1/_inputs.py
pulumi_ns1/_utilities.py
pulumi_ns1/account_whitelist.py
pulumi_ns1/alert.py
pulumi_ns1/api_key.py
pulumi_ns1/application.py
pulumi_ns1/data_feed.py
pulumi_ns1/data_source.py
pulumi_ns1/dataset.py
pulumi_ns1/dnsview.py
pulumi_ns1/get_billing_usage.py
pulumi_ns1/get_dns_sec.py
pulumi_ns1/get_monitoring_regions.py
pulumi_ns1/get_networks.py
pulumi_ns1/get_record.py
pulumi_ns1/get_zone.py
pulumi_ns1/monitoring_job.py
pulumi_ns1/notify_list.py
pulumi_ns1/outputs.py
pulumi_ns1/provider.py
pulumi_ns1/pulsar_job.py
pulumi_ns1/pulumi-plugin.json
pulumi_ns1/py.typed
pulumi_ns1/record.py
pulumi_ns1/redirect.py
pulumi_ns1/redirect_certificate.py
pulumi_ns1/team.py
pulumi_ns1/tsigkey.py
pulumi_ns1/user.py
pulumi_ns1/zone.py
pulumi_ns1/config/__init__.py
pulumi_ns1/config/__init__.pyi
pulumi_ns1/config/vars.py
pulumi_ns1-3.7.2.dist-info/METADATA
pulumi_ns1-3.7.2.dist-info/WHEEL
pulumi_ns1-3.7.2.dist-info/top_level.txt
pulumi_ns1-3.7.2.dist-info/RECORD
